aurflux/__init__.py
aurflux/abcs.py
aurflux/auth.py
aurflux/cog/__init__.py
aurflux/cog/builtins.py
aurflux/cog/fluxcog.py
aurflux/command/__init__.py
aurflux/command/argh.py
aurflux/command/command.py
aurflux/command/response.py
aurflux/config.py
aurflux/context/__init__.py
aurflux/context/context.py
aurflux/errors.py
aurflux/flux.py
aurflux/py.typed
aurflux/types_.py
aurflux/utils/__init__.py
aurflux/utils/date.py
aurflux/utils/discord.py
aurflux/utils/emoji.py
aurflux/utils/exec_.py
aurflux/utils/meta.py
aurflux/utils/misc.py
aurflux/utils/parsers.py
aurflux/utils/text.py
aurflux/utils/webutils.py
aurflux-4.0.6.dist-info/WHEEL
aurflux-4.0.6.dist-info/METADATA
aurflux-4.0.6.dist-info/RECORD
