Metadata-Version: 2.1
Name: aurflux
Version: 4.0.6
Summary: Aurflux!
Author: Zenith
Author-email: inbox@zenith.dev
Requires-Python: >=3.10
Classifier: Programming Language :: Python :: 3
Classifier: Programming Language :: Python :: 3.10
Requires-Dist: aurcore (>=1.1,<2.0)
Requires-Dist: dateparser (>=1.0.0,<2.0.0)
Requires-Dist: loguru (>=0.5.2,<0.6.0)
Requires-Dist: py-cord
Requires-Dist: pyyaml
Requires-Dist: tabulate (>=0.8.7,<0.9.0)
